spoton_generator/__init__.py
spoton_generator/__main__.py
spoton_generator/datagenerator.py
spoton_generator/factor.py
spoton_generator/group.py
spoton_generator/logger.py
spoton_generator/pattern.py
spoton_generator/persona.py
spoton_generator/question.py
spoton_generator/theme.py
spoton_generator/themerating.py
spoton_generator-0.1.5.dist-info/METADATA
spoton_generator-0.1.5.dist-info/WHEEL
spoton_generator-0.1.5.dist-info/top_level.txt
spoton_generator-0.1.5.dist-info/RECORD
