Metadata-Version: 2.1
Name: spoton-generator
Version: 0.1.5
Summary: A tool to generate data for Spot-On
Home-page: https://gitlab.forge.hefr.ch/pa-spot-on-demeusy/spot-on-generator
Author: Jean Demeusy
Author-email: dev.jdu@gmail.com
License: UNKNOWN
Platform: UNKNOWN
Classifier: Programming Language :: Python :: 3
Classifier: License :: OSI Approved :: MIT License
Classifier: Operating System :: OS Independent
Requires-Dist: spoton-soozaccess
Requires-Dist: matplotlib
Requires-Dist: numpy
